setup.py
WallpaperEntropy.egg-info/PKG-INFO
WallpaperEntropy.egg-info/SOURCES.txt
WallpaperEntropy.egg-info/dependency_links.txt
WallpaperEntropy.egg-info/requires.txt
WallpaperEntropy.egg-info/top_level.txt
entropy/__init__.py
entropy/__main__.py