Metadata-Version: 1.0
Name: WallpaperEntropy
Version: 0.1.0
Summary: A tool to rate potential wallpapers
Home-page: http://www.github.com/ExplosiveHippo/Entropy
Author: Dustin Raimondi, Chris Knepper, Lance Laughlin
Author-email: chris82thekid@gmail.com
License: LICENSE
Keywords: color wallpaper images image
Platform: UNKNOWN
